hyperpose/__init__.py
hyperpose/Config/__init__.py
hyperpose/Config/config_lopps.py
hyperpose/Config/config_mbtopps.py
hyperpose/Config/config_opps.py
hyperpose/Config/config_pifpaf.py
hyperpose/Config/config_ppn.py
hyperpose/Config/config_pretrain.py
hyperpose/Config/define.py
hyperpose/Dataset/__init__.py
hyperpose/Dataset/base_dataset.py
hyperpose/Dataset/common.py
hyperpose/Dataset/multi_dataset.py
hyperpose/Dataset/imagenet_dataset/__init__.py
hyperpose/Dataset/imagenet_dataset/dataset.py
hyperpose/Dataset/mpii_dataset/__init__.py
hyperpose/Dataset/mpii_dataset/dataset.py
hyperpose/Dataset/mpii_dataset/define.py
hyperpose/Dataset/mpii_dataset/format.py
hyperpose/Dataset/mpii_dataset/generate.py
hyperpose/Dataset/mpii_dataset/prepare.py
hyperpose/Dataset/mpii_dataset/utils.py
hyperpose/Dataset/mscoco_dataset/__init__.py
hyperpose/Dataset/mscoco_dataset/dataset.py
hyperpose/Dataset/mscoco_dataset/define.py
hyperpose/Dataset/mscoco_dataset/format.py
hyperpose/Dataset/mscoco_dataset/generate.py
hyperpose/Dataset/mscoco_dataset/prepare.py
hyperpose/Model/__init__.py
hyperpose/Model/augmentor.py
hyperpose/Model/backbones.py
hyperpose/Model/common.py
hyperpose/Model/domainadapt.py
hyperpose/Model/human.py
hyperpose/Model/metrics.py
hyperpose/Model/pretrain.py
hyperpose/Model/openpose/__init__.py
hyperpose/Model/openpose/define.py
hyperpose/Model/openpose/eval.py
hyperpose/Model/openpose/processor.py
hyperpose/Model/openpose/train.py
hyperpose/Model/openpose/utils.py
hyperpose/Model/openpose/model/__init__.py
hyperpose/Model/openpose/model/lw_openpose.py
hyperpose/Model/openpose/model/mbv2_sm_openpose.py
hyperpose/Model/openpose/model/mbv2_th_openpose.py
hyperpose/Model/openpose/model/openpose.py
hyperpose/Model/pifpaf/__init__.py
hyperpose/Model/pifpaf/define.py
hyperpose/Model/pifpaf/eval.py
hyperpose/Model/pifpaf/infer.py
hyperpose/Model/pifpaf/model.py
hyperpose/Model/pifpaf/processor.py
hyperpose/Model/pifpaf/train.py
hyperpose/Model/pifpaf/utils.py
hyperpose-2.2.0.dist-info/METADATA
hyperpose-2.2.0.dist-info/WHEEL
hyperpose-2.2.0.dist-info/top_level.txt
hyperpose-2.2.0.dist-info/RECORD
