Metadata-Version: 2.1
Name: hyperpose
Version: 2.2.0
Summary: HyperPose is a library for building human pose estimation systems that can efficiently operate in the wild.
Home-page: https://github.com/tensorlayer/hyperpose
Author: TensorLayer
Author-email: tensorlayer@gmail.com
License: Apache 2.0 license
Keywords: pose estimation platform
Platform: UNKNOWN
Requires-Dist: cython (>=0.29)
Requires-Dist: numpy (==1.16.4)
Requires-Dist: easydict (<=1.10,>=1.9)
Requires-Dist: opencv-python (<3.5,>=3.4)
Requires-Dist: tensorflow (==2.3.1)
Requires-Dist: tensorlayer (==2.2.3)
Requires-Dist: pycocotools
